COPYING
COPYING.lesser
NOTICE
README.md
setup.py
newmod/__init__.py
newmod.egg-info/PKG-INFO
newmod.egg-info/SOURCES.txt
newmod.egg-info/dependency_links.txt
newmod.egg-info/requires.txt
newmod.egg-info/top_level.txt
newmod/filters/__init__.py
newmod/filters/filters.py
newmod/helpers/__init__.py
newmod/helpers/helpers.py
newmod/listen/__init__.py
newmod/listen/listen.py
newmod/utils/__init__.py
newmod/utils/utils.py