Metadata-Version: 2.1
Name: newmod
Version: 0.0.3
Summary: Pyromod Custom, Experimental Noel
Home-page: https://github.com/jokokendi/pyromod
Author: jokokendi
Author-email: ajual7832@gmail.com
License: GPLv3
Download-URL: https://github.com/jokokendi/xmode/archive/v0.0.3.zip
Platform: UNKNOWN
Classifier: License :: OSI Approved :: MIT License
Classifier: Operating System :: OS Independent
Classifier: Programming Language :: Python
Classifier: Programming Language :: Python :: 3
Classifier: Programming Language :: Python :: 3.7
Classifier: Programming Language :: Python :: 3.8
Classifier: Programming Language :: Python :: 3.9
Classifier: Programming Language :: Python :: 3.10
Classifier: Programming Language :: Python :: 3.11
Requires-Python: ~=3.7
License-File: COPYING
License-File: COPYING.lesser
License-File: NOTICE
